asteroidpy/__init__.py
asteroidpy/asteroidpy.py
asteroidpy/configuration.py
asteroidpy/interface.py
asteroidpy/scheduling.py
asteroidpy-0.1.dist-info/licenses/LICENSE
tests/__init__.py
tests/test_configuration.py
tests/test_configuration_corrupted.py
tests/test_configuration_unittest.py
tests/test_configuration_unreadable.py
tests/test_scheduling.py
asteroidpy-0.1.dist-info/METADATA
asteroidpy-0.1.dist-info/WHEEL
asteroidpy-0.1.dist-info/top_level.txt
asteroidpy-0.1.dist-info/RECORD
