Metadata-Version: 2.4
Name: Asteroidpy
Version: 0.1
Summary: A tool for asteroid observation scheduling and analysis
Home-page: https://github.com/ziriuz84/asteroidpy
Author: Sirio Negri
Author-email: Sirio Negri <ziriuz84@gmail.com>
License-Expression: GPL-3.0
Project-URL: Homepage, https://github.com/ziriuz84/asteroidpy
Project-URL: Issues, https://github.com/ziriuz84/asteroidpy/issues
Classifier: Development Status :: 4 - Beta
Classifier: Intended Audience :: Science/Research
Classifier: Operating System :: POSIX :: Linux
Classifier: Programming Language :: Python :: 3
Requires-Python: >=3.9
License-File: LICENSE
Dynamic: author
Dynamic: home-page
Dynamic: license-file
